weegit/__init__.py
weegit/logger.py
weegit/settings.py
weegit/version.py
weegit/converter/__init__.py
weegit/converter/weegit_io.py
weegit/converter/source_reader/__init__.py
weegit/converter/source_reader/_exceptions.py
weegit/converter/source_reader/abstract_source_reader.py
weegit/converter/source_reader/edf_source_reader.py
weegit/converter/source_reader/intan_rhs_source_reader.py
weegit/converter/source_reader/old_weegit_reader.py
weegit/converter/source_reader/open_ephys_source_reader.py
weegit/converter/source_reader/source_reader_factory.py
weegit/core/__init__.py
weegit/core/exceptions.py
weegit/core/global_storage.py
weegit/core/header.py
weegit/core/weegit_session.py
weegit/core/analysis/__init__.py
weegit/core/analysis/script_template.py
weegit/core/conversions/__init__.py
weegit/core/conversions/filters.py
weegit/core/conversions/transformations.py
weegit/gui/__init__.py
weegit/gui/_utils.py
weegit/gui/entrypoint.py
weegit/gui/qt_weegit_session_manager_wrapper.py
weegit/gui/commands/__init__.py
weegit/gui/commands/base.py
weegit/gui/commands/events.py
weegit/gui/commands/periods.py
weegit/gui/dialogs/__init__.py
weegit/gui/dialogs/events_vocabulary_dialog.py
weegit/gui/dialogs/loading_dialog.py
weegit/gui/dialogs/periods_vocabulary_dialog.py
weegit/gui/dialogs/select_session_dialog.py
weegit/gui/dialogs/session_name_dialog.py
weegit/gui/mixins/__init__.py
weegit/gui/mixins/qwidget_mixin.py
weegit/gui/panels/__init__.py
weegit/gui/panels/analysis_panel.py
weegit/gui/panels/base_signal_panel.py
weegit/gui/panels/channels_description_panel.py
weegit/gui/panels/eeg_settings_panel.py
weegit/gui/panels/eeg_signal_panel.py
weegit/gui/panels/information_panel.py
weegit/gui/panels/logs_panel.py
weegit/gui/windows/__init__.py
weegit/gui/windows/main.py
weegit-0.0.20.dist-info/licenses/LICENSE
weegit-0.0.20.dist-info/METADATA
weegit-0.0.20.dist-info/WHEEL
weegit-0.0.20.dist-info/entry_points.txt
weegit-0.0.20.dist-info/top_level.txt
weegit-0.0.20.dist-info/RECORD
