Metadata-Version: 2.4
Name: weegit
Version: 0.0.20
Summary: Weegit - electrophysiology marking application
Author: LIFT center
Keywords: Weegit,EEG,electrophysiology,signal
Classifier: Programming Language :: Python :: 3
Classifier: Environment :: Console
Classifier: Environment :: Other Environment
Classifier: Environment :: Web Environment
Classifier: Intended Audience :: Developers
Classifier: Intended Audience :: End Users/Desktop
Classifier: License :: OSI Approved :: GNU General Public License v3 (GPLv3)
Classifier: Natural Language :: English
Classifier: Operating System :: OS Independent
Classifier: Programming Language :: Python
Classifier: Programming Language :: Python :: 3
Classifier: Programming Language :: Python :: 3.8
Classifier: Programming Language :: Python :: 3.9
Classifier: Programming Language :: Python :: 3.10
Classifier: Programming Language :: Python :: 3.11
Classifier: Programming Language :: Python :: 3.12
Classifier: Programming Language :: Python :: 3.13
Classifier: Programming Language :: Python :: 3.14
Classifier: Programming Language :: Python :: 3 :: Only
Requires-Python: >=3.9
License-File: LICENSE
Requires-Dist: PyQt6>=6.4.2
Requires-Dist: numpy~=2.2.0
Requires-Dist: pandas>=2.1.4
Requires-Dist: open-ephys-python-tools==0.1.13
Requires-Dist: pydantic>=2.11.9
Requires-Dist: platformdirs~=4.3.8
Requires-Dist: scipy>=1.12.0
Dynamic: license-file
